transpiler_mate/__about__.py
transpiler_mate/__init__.py
transpiler_mate/cli.py
transpiler_mate/codemeta.py
transpiler_mate/invenio.py
transpiler_mate/datacite/__init__.py
transpiler_mate/datacite/datacite_4_6_models.py
transpiler_mate/markdown/__init__.py
transpiler_mate/markdown/templates/index.md
transpiler_mate/markdown/templates/metadata.md
transpiler_mate/markdown/templates/workflow.md
transpiler_mate/metadata/__init__.py
transpiler_mate/metadata/licenses.py
transpiler_mate/metadata/software_application_models.py
transpiler_mate/ogcapi_records/__init__.py
transpiler_mate/ogcapi_records/ogcapi_records_models.py
transpiler_mate/ogcapi_records/sciencekeywords.py
transpiler_mate-0.23.0.dist-info/METADATA
transpiler_mate-0.23.0.dist-info/WHEEL
transpiler_mate-0.23.0.dist-info/entry_points.txt
transpiler_mate-0.23.0.dist-info/licenses/LICENSE
transpiler_mate-0.23.0.dist-info/licenses/NOTICE
transpiler_mate-0.23.0.dist-info/RECORD
