Metadata-Version: 2.4
Name: transpiler-mate
Version: 0.23.0
Summary: Schema.org 2 metadata formats transpiler
Project-URL: Documentation, https://github.com/Terradue/transpiler-mate#readme
Project-URL: Issues, https://github.com/Terradue/transpiler-mate/issues
Project-URL: Source, https://github.com/Terradue/transpiler-mate
Author-email: Fabrice Brito <info@terradue.com>, Simone Tripodi <info@terradue.com>
License-Expression: Apache-2.0
License-File: LICENSE
License-File: NOTICE
Classifier: Development Status :: 4 - Beta
Classifier: Programming Language :: Python
Classifier: Programming Language :: Python :: 3.8
Classifier: Programming Language :: Python :: 3.9
Classifier: Programming Language :: Python :: 3.10
Classifier: Programming Language :: Python :: 3.11
Classifier: Programming Language :: Python :: 3.12
Classifier: Programming Language :: Python :: Implementation :: CPython
Classifier: Programming Language :: Python :: Implementation :: PyPy
Requires-Python: >=3.8
Requires-Dist: click>=8.3.0
Requires-Dist: cwl-loader
Requires-Dist: email-validator
Requires-Dist: giturlparse
Requires-Dist: invenio-rest-api-client
Requires-Dist: jinja2>=3.1.6
Requires-Dist: loguru
Requires-Dist: pydantic
Requires-Dist: ruamel-yaml>=0.18.16
Requires-Dist: semver
Requires-Dist: yaml-ld
